mathisonturing/__init__.py
mathisonturing/tools.py
MathisonTuring-0.0.6.dist-info/METADATA
MathisonTuring-0.0.6.dist-info/WHEEL
MathisonTuring-0.0.6.dist-info/top_level.txt
MathisonTuring-0.0.6.dist-info/RECORD
