Metadata-Version: 2.1
Name: MathisonTuring
Version: 0.0.6
Summary: Mathison Turing Python SDK
Home-page: UNKNOWN
Author: Daniel David
Author-email: daniel.david@mathisonturing.com
License: GPL
Platform: UNKNOWN
Classifier: Programming Language :: Python :: 3.7
Requires-Dist: Pyrebase
Requires-Dist: json
Requires-Dist: validict
